{
  "timestamp": "2026-03-25T19:40:02.899Z",
  "serverUptime": 1419858,
  "loadAvg": [
    "0.18",
    "0.19",
    "0.15"
  ],
  "topics": [
    {
      "topicId": "1",
      "name": "General",
      "status": "working",
      "statusLabel": "🔵 Working",
      "lastUpdate": "2026-03-25T19:39:59.660Z",
      "ageSec": 3,
      "tokens": 81524,
      "lastAction": "Добър въпрос. Нека гледам обективно — по impact × текущо качество:  | Skill | Размер | Ползване | Качество | Impact ако",
      "hasProcess": false,
      "hasSession": true
    },
    {
      "topicId": "6",
      "name": "📝 Daily Notes",
      "status": "idle",
      "statusLabel": "⚪ Idle",
      "lastUpdate": null,
      "ageSec": 999999,
      "tokens": 0,
      "lastAction": "",
      "hasProcess": false,
      "hasSession": false
    },
    {
      "topicId": "7",
      "name": "Sales Training",
      "status": "idle",
      "statusLabel": "⚪ Idle",
      "lastUpdate": null,
      "ageSec": 999999,
      "tokens": 0,
      "lastAction": "",
      "hasProcess": false,
      "hasSession": false
    },
    {
      "topicId": "8",
      "name": "🔍 Niche Research",
      "status": "idle",
      "statusLabel": "⚪ Idle",
      "lastUpdate": null,
      "ageSec": 999999,
      "tokens": 0,
      "lastAction": "",
      "hasProcess": false,
      "hasSession": false
    },
    {
      "topicId": "9",
      "name": "📊 Reports",
      "status": "idle",
      "statusLabel": "⚪ Idle",
      "lastUpdate": null,
      "ageSec": 999999,
      "tokens": 0,
      "lastAction": "",
      "hasProcess": false,
      "hasSession": false
    },
    {
      "topicId": "10",
      "name": "💡 Strategy & Ideas",
      "status": "idle",
      "statusLabel": "⚪ Idle",
      "lastUpdate": null,
      "ageSec": 999999,
      "tokens": 0,
      "lastAction": "",
      "hasProcess": false,
      "hasSession": false
    },
    {
      "topicId": "11",
      "name": "📥 Inbox",
      "status": "idle",
      "statusLabel": "⚪ Idle",
      "lastUpdate": "2026-03-24T16:15:07.513Z",
      "ageSec": 98695,
      "tokens": 20441,
      "lastAction": "",
      "hasProcess": false,
      "hasSession": true
    },
    {
      "topicId": "49",
      "name": "Demo Sites",
      "status": "idle",
      "statusLabel": "⚪ Idle",
      "lastUpdate": "2026-03-25T15:41:09.902Z",
      "ageSec": 14332,
      "tokens": 76764,
      "lastAction": "Крис, ситуацията е ясна:  **Какво стана с Финкомекс:** - Ревизията **Е направена** ✅ (commit от 15:29 UTC — логото е доб",
      "hasProcess": false,
      "hasSession": true
    },
    {
      "topicId": "50",
      "name": "RunAI Coach",
      "status": "idle",
      "statusLabel": "⚪ Idle",
      "lastUpdate": null,
      "ageSec": 999999,
      "tokens": 0,
      "lastAction": "",
      "hasProcess": false,
      "hasSession": false
    },
    {
      "topicId": "51",
      "name": "Momerly",
      "status": "idle",
      "statusLabel": "⚪ Idle",
      "lastUpdate": null,
      "ageSec": 999999,
      "tokens": 0,
      "lastAction": "",
      "hasProcess": false,
      "hasSession": false
    },
    {
      "topicId": "718",
      "name": "OpenClaw Service",
      "status": "idle",
      "statusLabel": "⚪ Idle",
      "lastUpdate": null,
      "ageSec": 999999,
      "tokens": 0,
      "lastAction": "",
      "hasProcess": false,
      "hasSession": false
    },
    {
      "topicId": "1648",
      "name": "X Audience Challenges",
      "status": "idle",
      "statusLabel": "⚪ Idle",
      "lastUpdate": null,
      "ageSec": 999999,
      "tokens": 0,
      "lastAction": "",
      "hasProcess": false,
      "hasSession": false
    }
  ],
  "processes": [],
  "errors": {
    "recent": [],
    "counts": {}
  },
  "summary": {
    "totalTopics": 12,
    "working": 1,
    "building": 0,
    "recent": 0,
    "idle": 11,
    "stuck": 0
  }
}